LICENSE
README.md
setup.py
burmese_number_converter/__init__.py
burmese_number_converter/convert_burmese_string_to_datetime.py
burmese_number_converter.egg-info/PKG-INFO
burmese_number_converter.egg-info/SOURCES.txt
burmese_number_converter.egg-info/dependency_links.txt
burmese_number_converter.egg-info/not-zip-safe
burmese_number_converter.egg-info/top_level.txt