Metadata-Version: 2.1
Name: burmese-number-converter
Version: 1.0.0
Summary: Convert English Number to Burmese Number
Home-page: https://github.com/HanZawNyein/odoo-rest-framework.git
Author: Han Zaw Nyein
Author-email: hanzawnyineonline@gmail.com
License: UNKNOWN
Platform: UNKNOWN
License-File: LICENSE
